prokill/__init__.py
prokill/__main__.py
prokill/prokill.py
prokill-1.3.0.dist-info/METADATA
prokill-1.3.0.dist-info/WHEEL
prokill-1.3.0.dist-info/entry_points.txt
prokill-1.3.0.dist-info/top_level.txt
prokill-1.3.0.dist-info/RECORD
