Metadata-Version: 2.2
Name: prokill
Version: 1.3.0
Summary: prokill
Classifier: Operating System :: OS Independent
Classifier: Programming Language :: Python
Classifier: Programming Language :: Python :: 3.10
Classifier: Programming Language :: Python :: 3.11
Requires-Python: >=3.10
Requires-Dist: WMI
